build/lib/build/lib/spoticli/ViewManager.py
build/lib/build/lib/spoticli/__init__.py
build/lib/build/lib/spoticli/__main__.py
build/lib/build/lib/spoticli/Components/__init__.py
build/lib/build/lib/spoticli/Components/Main/HelpMenu.py
build/lib/build/lib/spoticli/Components/Main/Log.py
build/lib/build/lib/spoticli/Components/Main/Lyrics.py
build/lib/build/lib/spoticli/Components/Main/MainMenu.py
build/lib/build/lib/spoticli/Components/Main/Player.py
build/lib/build/lib/spoticli/Components/Main/Playlist.py
build/lib/build/lib/spoticli/Components/Main/PlaylistMenu.py
build/lib/build/lib/spoticli/Components/Main/SongItem.py
build/lib/build/lib/spoticli/Components/Main/TitleBar.py
build/lib/build/lib/spoticli/Components/Main/ViewManager.py
build/lib/build/lib/spoticli/Components/Main/__init__.py
build/lib/build/lib/spoticli/Components/Templates/Component.py
build/lib/build/lib/spoticli/Components/Templates/Menu.py
build/lib/build/lib/spoticli/Components/Templates/TextLines.py
build/lib/build/lib/spoticli/Components/Templates/__init__.py
build/lib/build/lib/spoticli/Utils/DataFiles.py
build/lib/build/lib/spoticli/Utils/__init__.py
build/lib/build/lib/spoticli/Utils/api.py
build/lib/build/lib/spoticli/Utils/authenticate.py
build/lib/build/lib/spoticli/Utils/lyrics.py
build/lib/build/lib/spoticli/Utils/server.py
build/lib/build/lib/spoticli/Utils/settings.py
build/lib/build/lib/spoticli/Utils/shortcuts.py
build/lib/build/lib/spoticli/Utils/utils.py
build/lib/spoticli/ViewManager.py
build/lib/spoticli/__init__.py
build/lib/spoticli/__main__.py
build/lib/spoticli/Components/__init__.py
build/lib/spoticli/Components/Main/HelpMenu.py
build/lib/spoticli/Components/Main/Log.py
build/lib/spoticli/Components/Main/Lyrics.py
build/lib/spoticli/Components/Main/MainMenu.py
build/lib/spoticli/Components/Main/Player.py
build/lib/spoticli/Components/Main/Playlist.py
build/lib/spoticli/Components/Main/PlaylistMenu.py
build/lib/spoticli/Components/Main/SongItem.py
spoti_cli-1.0.1.dist-info/METADATA
spoti_cli-1.0.1.dist-info/WHEEL
spoti_cli-1.0.1.dist-info/entry_points.txt
spoti_cli-1.0.1.dist-info/top_level.txt
spoti_cli-1.0.1.dist-info/RECORD
