Metadata-Version: 2.1
Name: spoti-cli
Version: 1.0.1
Summary: Terminal based Spotify client designed to use Vim keybindings.
Home-page: https://github.com/joeysnclr/spoti-cli
Author: Joseph Sinclair
Author-email: joey.sinclair02@gmail.com
License: MIT
Platform: UNKNOWN
Classifier: License :: OSI Approved :: MIT License
Classifier: Programming Language :: Python :: 3
Classifier: Programming Language :: Python :: 3.8
Requires-Dist: wheel
Requires-Dist: beautifulsoup4
Requires-Dist: blessed
Requires-Dist: Flask
Requires-Dist: requests
